vibehowmanyrs/__init__.py
vibehowmanyrs/ai.py
vibehowmanyrs/py.typed
vibehowmanyrs-0.1.0.dist-info/METADATA
vibehowmanyrs-0.1.0.dist-info/WHEEL
vibehowmanyrs-0.1.0.dist-info/licenses/LICENSE
vibehowmanyrs-0.1.0.dist-info/RECORD
